{"MODULE_SK":25,"DATAFLOW_NAME":"INDEXING POLYGON","MODULE_NAME":"CLEAN_INDEX_POLYGON","MODULE_SOFTWARE_VERS":"1.1","COMMIT_THRESHOLD":10000,"MODULE_RUN_STATUS_SK":5,"MODULE_STOP_IND":"N","DWH_START_DATE":"Mar 7, 2012","DWH_END_DATE":"Jun 18, 2012","DWH_VERS":1,"childData":[{"MODULE_RUN_SK":497,"MODULE_SK":25,"MODULE_RUN_STATUS_SK":3,"START_DATE":"May 2, 2012","COMPLETE_DATE":"May 2, 2012","ROWS_READ":0,"ROWS_WRITTEN":0},{"MODULE_RUN_SK":516,"MODULE_SK":25,"MODULE_RUN_STATUS_SK":3,"START_DATE":"May 3, 2012","COMPLETE_DATE":"May 3, 2012","ROWS_READ":0,"ROWS_WRITTEN":0},{"MODULE_RUN_SK":417,"MODULE_SK":25,"MODULE_RUN_STATUS_SK":3,"START_DATE":"Apr 26, 2012","COMPLETE_DATE":"Apr 26, 2012","ROWS_READ":0,"ROWS_WRITTEN":0},{"MODULE_RUN_SK":437,"MODULE_SK":25,"MODULE_RUN_STATUS_SK":3,"START_DATE":"Apr 27, 2012","COMPLETE_DATE":"Apr 27, 2012","ROWS_READ":0,"ROWS_WRITTEN":0},{"MODULE_RUN_SK":477,"MODULE_SK":25,"MODULE_RUN_STATUS_SK":3,"START_DATE":"May 1, 2012","COMPLETE_DATE":"May 1, 2012","ROWS_READ":0,"ROWS_WRITTEN":0},{"MODULE_RUN_SK":654,"MODULE_SK":25,"MODULE_RUN_STATUS_SK":3,"START_DATE":"May 12, 2012","COMPLETE_DATE":"May 12, 2012","ROWS_READ":0,"ROWS_WRITTEN":0},{"MODULE_RUN_SK":274,"MODULE_SK":25,"MODULE_RUN_STATUS_SK":3,"START_DATE":"Apr 11, 2012","COMPLETE_DATE":"Apr 11, 2012","ROWS_READ":0,"ROWS_WRITTEN":0},{"MODULE_RUN_SK":302,"MODULE_SK":25,"MODULE_RUN_STATUS_SK":3,"START_DATE":"Apr 17, 2012","COMPLETE_DATE":"Apr 17, 2012","ROWS_READ":0,"ROWS_WRITTEN":0},{"MODULE_RUN_SK":397,"MODULE_SK":25,"MODULE_RUN_STATUS_SK":3,"START_DATE":"Apr 25, 2012","COMPLETE_DATE":"Apr 25, 2012","ROWS_READ":0,"ROWS_WRITTEN":0},{"MODULE_RUN_SK":594,"MODULE_SK":25,"MODULE_RUN_STATUS_SK":3,"START_DATE":"May 9, 2012","COMPLETE_DATE":"May 9, 2012","ROWS_READ":0,"ROWS_WRITTEN":0},{"MODULE_RUN_SK":614,"MODULE_SK":25,"MODULE_RUN_STATUS_SK":3,"START_DATE":"May 10, 2012","COMPLETE_DATE":"May 10, 2012","ROWS_READ":0,"ROWS_WRITTEN":0},{"MODULE_RUN_SK":633,"MODULE_SK":25,"MODULE_RUN_STATUS_SK":3,"START_DATE":"May 11, 2012","COMPLETE_DATE":"May 11, 2012","ROWS_READ":0,"ROWS_WRITTEN":0},{"MODULE_RUN_SK":714,"MODULE_SK":25,"MODULE_RUN_STATUS_SK":3,"START_DATE":"May 17, 2012","COMPLETE_DATE":"May 17, 2012","ROWS_READ":0,"ROWS_WRITTEN":0},{"MODULE_RUN_SK":1047,"MODULE_SK":25,"MODULE_RUN_STATUS_SK":3,"START_DATE":"Jun 12, 2012","COMPLETE_DATE":"Jun 12, 2012","ROWS_READ":0,"ROWS_WRITTEN":0},{"MODULE_RUN_SK":327,"MODULE_SK":25,"MODULE_RUN_STATUS_SK":3,"START_DATE":"Apr 19, 2012","COMPLETE_DATE":"Apr 19, 2012","ROWS_READ":0,"ROWS_WRITTEN":0},{"MODULE_RUN_SK":377,"MODULE_SK":25,"MODULE_RUN_STATUS_SK":3,"START_DATE":"Apr 24, 2012","COMPLETE_DATE":"Apr 24, 2012","ROWS_READ":0,"ROWS_WRITTEN":0},{"MODULE_RUN_SK":537,"MODULE_SK":25,"MODULE_RUN_STATUS_SK":3,"START_DATE":"May 4, 2012","COMPLETE_DATE":"May 4, 2012","ROWS_READ":0,"ROWS_WRITTEN":0},{"MODULE_RUN_SK":557,"MODULE_SK":25,"MODULE_RUN_STATUS_SK":3,"START_DATE":"May 5, 2012","COMPLETE_DATE":"May 5, 2012","ROWS_READ":0,"ROWS_WRITTEN":0},{"MODULE_RUN_SK":318,"MODULE_SK":25,"MODULE_RUN_STATUS_SK":3,"START_DATE":"Apr 18, 2012","COMPLETE_DATE":"Apr 18, 2012","ROWS_READ":0,"ROWS_WRITTEN":0},{"MODULE_RUN_SK":358,"MODULE_SK":25,"MODULE_RUN_STATUS_SK":3,"START_DATE":"Apr 21, 2012","COMPLETE_DATE":"Apr 21, 2012","ROWS_READ":0,"ROWS_WRITTEN":0},{"MODULE_RUN_SK":457,"MODULE_SK":25,"MODULE_RUN_STATUS_SK":3,"START_DATE":"Apr 28, 2012","COMPLETE_DATE":"Apr 28, 2012","ROWS_READ":0,"ROWS_WRITTEN":0},{"MODULE_RUN_SK":867,"MODULE_SK":25,"MODULE_RUN_STATUS_SK":3,"START_DATE":"May 29, 2012","COMPLETE_DATE":"May 29, 2012","ROWS_READ":0,"ROWS_WRITTEN":0},{"MODULE_RUN_SK":990,"MODULE_SK":25,"MODULE_RUN_STATUS_SK":3,"START_DATE":"Jun 7, 2012","COMPLETE_DATE":"Jun 7, 2012","ROWS_READ":0,"ROWS_WRITTEN":0},{"MODULE_RUN_SK":1067,"MODULE_SK":25,"MODULE_RUN_STATUS_SK":3,"START_DATE":"Jun 13, 2012","COMPLETE_DATE":"Jun 13, 2012","ROWS_READ":0,"ROWS_WRITTEN":0},{"MODULE_RUN_SK":919,"MODULE_SK":25,"MODULE_RUN_STATUS_SK":3,"START_DATE":"Jun 1, 2012","COMPLETE_DATE":"Jun 1, 2012","ROWS_READ":0,"ROWS_WRITTEN":0},{"MODULE_RUN_SK":1010,"MODULE_SK":25,"MODULE_RUN_STATUS_SK":3,"START_DATE":"Jun 8, 2012","COMPLETE_DATE":"Jun 8, 2012","ROWS_READ":0,"ROWS_WRITTEN":0},{"MODULE_RUN_SK":1029,"MODULE_SK":25,"MODULE_RUN_STATUS_SK":3,"START_DATE":"Jun 9, 2012","COMPLETE_DATE":"Jun 9, 2012","ROWS_READ":0,"ROWS_WRITTEN":0},{"MODULE_RUN_SK":809,"MODULE_SK":25,"MODULE_RUN_STATUS_SK":3,"START_DATE":"May 24, 2012","COMPLETE_DATE":"May 24, 2012","ROWS_READ":0,"ROWS_WRITTEN":0},{"MODULE_RUN_SK":828,"MODULE_SK":25,"MODULE_RUN_STATUS_SK":3,"START_DATE":"May 25, 2012","COMPLETE_DATE":"May 25, 2012","ROWS_READ":0,"ROWS_WRITTEN":0},{"MODULE_RUN_SK":770,"MODULE_SK":25,"MODULE_RUN_STATUS_SK":3,"START_DATE":"May 22, 2012","COMPLETE_DATE":"May 22, 2012","ROWS_READ":0,"ROWS_WRITTEN":0},{"MODULE_RUN_SK":790,"MODULE_SK":25,"MODULE_RUN_STATUS_SK":3,"START_DATE":"May 23, 2012","COMPLETE_DATE":"May 23, 2012","ROWS_READ":0,"ROWS_WRITTEN":0},{"MODULE_RUN_SK":848,"MODULE_SK":25,"MODULE_RUN_STATUS_SK":3,"START_DATE":"May 26, 2012","COMPLETE_DATE":"May 26, 2012","ROWS_READ":0,"ROWS_WRITTEN":0},{"MODULE_RUN_SK":674,"MODULE_SK":25,"MODULE_RUN_STATUS_SK":3,"START_DATE":"May 15, 2012","COMPLETE_DATE":"May 15, 2012","ROWS_READ":0,"ROWS_WRITTEN":0},{"MODULE_RUN_SK":734,"MODULE_SK":25,"MODULE_RUN_STATUS_SK":3,"START_DATE":"May 18, 2012","COMPLETE_DATE":"May 18, 2012","ROWS_READ":0,"ROWS_WRITTEN":0},{"MODULE_RUN_SK":900,"MODULE_SK":25,"MODULE_RUN_STATUS_SK":3,"START_DATE":"May 31, 2012","COMPLETE_DATE":"May 31, 2012","ROWS_READ":0,"ROWS_WRITTEN":0},{"MODULE_RUN_SK":694,"MODULE_SK":25,"MODULE_RUN_STATUS_SK":3,"START_DATE":"May 16, 2012","COMPLETE_DATE":"May 16, 2012","ROWS_READ":0,"ROWS_WRITTEN":0},{"MODULE_RUN_SK":938,"MODULE_SK":25,"MODULE_RUN_STATUS_SK":3,"START_DATE":"Jun 2, 2012","COMPLETE_DATE":"Jun 2, 2012","ROWS_READ":0,"ROWS_WRITTEN":0}]}