{"MODULE_SK":725,"DATAFLOW_NAME":"ENTRY_INFLL_HIST","MODULE_NAME":"PROCESS_ENTRY_INFLL_HIST","MODULE_SOFTWARE_VERS":"4.0","COMMIT_THRESHOLD":10000,"MODULE_RUN_STATUS_SK":5,"MODULE_STOP_IND":"N","DWH_START_DATE":"Mar 20, 2014","DWH_VERS":1,"childData":[{"MODULE_RUN_SK":35839,"MODULE_SK":725,"MODULE_RUN_STATUS_SK":3,"START_DATE":"Apr 10, 2014","COMPLETE_DATE":"Apr 10, 2014","ROWS_READ":6,"ROWS_WRITTEN":5,"CONTEXT_VERS":"11"},{"MODULE_RUN_SK":35840,"MODULE_SK":725,"MODULE_RUN_STATUS_SK":3,"START_DATE":"Apr 10, 2014","COMPLETE_DATE":"Apr 10, 2014","ROWS_READ":1,"ROWS_WRITTEN":0,"CONTEXT_VERS":"11"},{"MODULE_RUN_SK":35864,"MODULE_SK":725,"MODULE_RUN_STATUS_SK":3,"START_DATE":"Apr 10, 2014","COMPLETE_DATE":"Apr 10, 2014","ROWS_READ":1,"ROWS_WRITTEN":1,"CONTEXT_VERS":"11"},{"MODULE_RUN_SK":35180,"MODULE_SK":725,"MODULE_RUN_STATUS_SK":3,"START_DATE":"Mar 25, 2014","COMPLETE_DATE":"Mar 25, 2014","ROWS_READ":18,"ROWS_WRITTEN":18,"CONTEXT_VERS":"11"},{"MODULE_RUN_SK":35171,"MODULE_SK":725,"MODULE_RUN_STATUS_SK":3,"START_DATE":"Mar 25, 2014","COMPLETE_DATE":"Mar 25, 2014","ROWS_READ":1,"ROWS_WRITTEN":1,"CONTEXT_VERS":"11"},{"MODULE_RUN_SK":35168,"MODULE_SK":725,"MODULE_RUN_STATUS_SK":3,"START_DATE":"Mar 25, 2014","COMPLETE_DATE":"Mar 25, 2014","ROWS_READ":12,"ROWS_WRITTEN":12,"CONTEXT_VERS":"11"},{"MODULE_RUN_SK":35181,"MODULE_SK":725,"MODULE_RUN_STATUS_SK":3,"START_DATE":"Mar 25, 2014","COMPLETE_DATE":"Mar 25, 2014","ROWS_READ":2,"ROWS_WRITTEN":2,"CONTEXT_VERS":"11"},{"MODULE_RUN_SK":35862,"MODULE_SK":725,"MODULE_RUN_STATUS_SK":3,"START_DATE":"Apr 10, 2014","COMPLETE_DATE":"Apr 10, 2014","ROWS_READ":1,"ROWS_WRITTEN":1,"CONTEXT_VERS":"11"},{"MODULE_RUN_SK":35169,"MODULE_SK":725,"MODULE_RUN_STATUS_SK":3,"START_DATE":"Mar 25, 2014","COMPLETE_DATE":"Mar 25, 2014","ROWS_READ":2,"ROWS_WRITTEN":2,"CONTEXT_VERS":"11"},{"MODULE_RUN_SK":35863,"MODULE_SK":725,"MODULE_RUN_STATUS_SK":3,"START_DATE":"Apr 10, 2014","COMPLETE_DATE":"Apr 10, 2014","ROWS_READ":0,"ROWS_WRITTEN":0,"CONTEXT_VERS":"11"}]}