{"MODULE_SK":89,"DATAFLOW_NAME":"INDEXING EXTENT","MODULE_NAME":"PROCESS_INDEXING_EXTENT","MODULE_SOFTWARE_VERS":"3.0","COMMIT_THRESHOLD":10000,"MODULE_RUN_STATUS_SK":5,"MODULE_STOP_IND":"N","DWH_START_DATE":"Jun 29, 2012","DWH_END_DATE":"Oct 19, 2012","DWH_VERS":3,"childData":[{"MODULE_RUN_SK":1453,"MODULE_SK":89,"MODULE_RUN_STATUS_SK":3,"START_DATE":"Jul 3, 2012","COMPLETE_DATE":"Jul 3, 2012","ROWS_READ":17521,"ROWS_WRITTEN":13715,"CONTEXT_VERS":"09"},{"MODULE_RUN_SK":1662,"MODULE_SK":89,"MODULE_RUN_STATUS_SK":3,"START_DATE":"Jul 18, 2012","COMPLETE_DATE":"Jul 18, 2012","ROWS_READ":22040,"ROWS_WRITTEN":17425,"CONTEXT_VERS":"09"},{"MODULE_RUN_SK":1681,"MODULE_SK":89,"MODULE_RUN_STATUS_SK":3,"START_DATE":"Jul 19, 2012","COMPLETE_DATE":"Jul 19, 2012","ROWS_READ":23582,"ROWS_WRITTEN":17396,"CONTEXT_VERS":"09"},{"MODULE_RUN_SK":1866,"MODULE_SK":89,"MODULE_RUN_STATUS_SK":3,"START_DATE":"Aug 1, 2012","COMPLETE_DATE":"Aug 1, 2012","ROWS_READ":16384,"ROWS_WRITTEN":12954,"CONTEXT_VERS":"09"},{"MODULE_RUN_SK":2321,"MODULE_SK":89,"MODULE_RUN_STATUS_SK":3,"START_DATE":"Sep 4, 2012","COMPLETE_DATE":"Sep 4, 2012","ROWS_READ":13791,"ROWS_WRITTEN":11973,"CONTEXT_VERS":"09"},{"MODULE_RUN_SK":2039,"MODULE_SK":89,"MODULE_RUN_STATUS_SK":3,"START_DATE":"Aug 14, 2012","COMPLETE_DATE":"Aug 14, 2012","ROWS_READ":13410,"ROWS_WRITTEN":10278,"CONTEXT_VERS":"09"},{"MODULE_RUN_SK":2058,"MODULE_SK":89,"MODULE_RUN_STATUS_SK":3,"START_DATE":"Aug 15, 2012","COMPLETE_DATE":"Aug 15, 2012","ROWS_READ":17540,"ROWS_WRITTEN":14509,"CONTEXT_VERS":"09"},{"MODULE_RUN_SK":2096,"MODULE_SK":89,"MODULE_RUN_STATUS_SK":1,"START_DATE":"Aug 17, 2012","ROWS_READ":0,"ROWS_WRITTEN":0,"CONTEXT_VERS":"09"},{"MODULE_RUN_SK":2097,"MODULE_SK":89,"MODULE_RUN_STATUS_SK":3,"START_DATE":"Aug 17, 2012","COMPLETE_DATE":"Aug 17, 2012","ROWS_READ":3430,"ROWS_WRITTEN":0,"CONTEXT_VERS":"09"},{"MODULE_RUN_SK":2154,"MODULE_SK":89,"MODULE_RUN_STATUS_SK":3,"START_DATE":"Aug 22, 2012","COMPLETE_DATE":"Aug 22, 2012","ROWS_READ":22644,"ROWS_WRITTEN":18325,"CONTEXT_VERS":"09"},{"MODULE_RUN_SK":1472,"MODULE_SK":89,"MODULE_RUN_STATUS_SK":3,"START_DATE":"Jul 4, 2012","COMPLETE_DATE":"Jul 4, 2012","ROWS_READ":18614,"ROWS_WRITTEN":14575,"CONTEXT_VERS":"09"},{"MODULE_RUN_SK":1548,"MODULE_SK":89,"MODULE_RUN_STATUS_SK":3,"START_DATE":"Jul 10, 2012","COMPLETE_DATE":"Jul 10, 2012","ROWS_READ":15458,"ROWS_WRITTEN":11732,"CONTEXT_VERS":"09"},{"MODULE_RUN_SK":1700,"MODULE_SK":89,"MODULE_RUN_STATUS_SK":3,"START_DATE":"Jul 20, 2012","COMPLETE_DATE":"Jul 20, 2012","ROWS_READ":21156,"ROWS_WRITTEN":16327,"CONTEXT_VERS":"09"},{"MODULE_RUN_SK":2116,"MODULE_SK":89,"MODULE_RUN_STATUS_SK":3,"START_DATE":"Aug 18, 2012","COMPLETE_DATE":"Aug 18, 2012","ROWS_READ":16914,"ROWS_WRITTEN":12721,"CONTEXT_VERS":"09"},{"MODULE_RUN_SK":2192,"MODULE_SK":89,"MODULE_RUN_STATUS_SK":3,"START_DATE":"Aug 24, 2012","COMPLETE_DATE":"Aug 24, 2012","ROWS_READ":16217,"ROWS_WRITTEN":13762,"CONTEXT_VERS":"09"},{"MODULE_RUN_SK":2245,"MODULE_SK":89,"MODULE_RUN_STATUS_SK":3,"START_DATE":"Aug 29, 2012","COMPLETE_DATE":"Aug 29, 2012","ROWS_READ":52512,"ROWS_WRITTEN":44905,"CONTEXT_VERS":"09"},{"MODULE_RUN_SK":1434,"MODULE_SK":89,"MODULE_RUN_STATUS_SK":3,"START_DATE":"Jul 2, 2012","COMPLETE_DATE":"Jul 2, 2012","ROWS_READ":16212,"ROWS_WRITTEN":12274,"CONTEXT_VERS":"09"},{"MODULE_RUN_SK":1885,"MODULE_SK":89,"MODULE_RUN_STATUS_SK":2,"START_DATE":"Aug 2, 2012","COMPLETE_DATE":"Aug 2, 2012","ROWS_READ":0,"ROWS_WRITTEN":0,"CONTEXT_VERS":"09"},{"MODULE_RUN_SK":1904,"MODULE_SK":89,"MODULE_RUN_STATUS_SK":2,"START_DATE":"Aug 3, 2012","COMPLETE_DATE":"Aug 3, 2012","ROWS_READ":0,"ROWS_WRITTEN":0,"CONTEXT_VERS":"09"},{"MODULE_RUN_SK":2340,"MODULE_SK":89,"MODULE_RUN_STATUS_SK":3,"START_DATE":"Sep 5, 2012","COMPLETE_DATE":"Sep 5, 2012","ROWS_READ":16709,"ROWS_WRITTEN":13218,"CONTEXT_VERS":"09"},{"MODULE_RUN_SK":2435,"MODULE_SK":89,"MODULE_RUN_STATUS_SK":3,"START_DATE":"Sep 12, 2012","COMPLETE_DATE":"Sep 12, 2012","ROWS_READ":19164,"ROWS_WRITTEN":15045,"CONTEXT_VERS":"09"},{"MODULE_RUN_SK":2473,"MODULE_SK":89,"MODULE_RUN_STATUS_SK":3,"START_DATE":"Sep 14, 2012","COMPLETE_DATE":"Sep 14, 2012","ROWS_READ":14978,"ROWS_WRITTEN":12312,"CONTEXT_VERS":"09"},{"MODULE_RUN_SK":1605,"MODULE_SK":89,"MODULE_RUN_STATUS_SK":3,"START_DATE":"Jul 13, 2012","COMPLETE_DATE":"Jul 13, 2012","ROWS_READ":28515,"ROWS_WRITTEN":21117,"CONTEXT_VERS":"09"},{"MODULE_RUN_SK":1795,"MODULE_SK":89,"MODULE_RUN_STATUS_SK":3,"START_DATE":"Jul 27, 2012","COMPLETE_DATE":"Jul 27, 2012","ROWS_READ":23652,"ROWS_WRITTEN":19531,"CONTEXT_VERS":"09"},{"MODULE_RUN_SK":1833,"MODULE_SK":89,"MODULE_RUN_STATUS_SK":3,"START_DATE":"Jul 31, 2012","COMPLETE_DATE":"Jul 31, 2012","ROWS_READ":16405,"ROWS_WRITTEN":12971,"CONTEXT_VERS":"09"},{"MODULE_RUN_SK":1925,"MODULE_SK":89,"MODULE_RUN_STATUS_SK":3,"START_DATE":"Aug 6, 2012","COMPLETE_DATE":"Aug 6, 2012","ROWS_READ":14627,"ROWS_WRITTEN":0,"CONTEXT_VERS":"09"},{"MODULE_RUN_SK":1814,"MODULE_SK":89,"MODULE_RUN_STATUS_SK":3,"START_DATE":"Jul 28, 2012","COMPLETE_DATE":"Jul 28, 2012","ROWS_READ":17009,"ROWS_WRITTEN":12816,"CONTEXT_VERS":"09"},{"MODULE_RUN_SK":1963,"MODULE_SK":89,"MODULE_RUN_STATUS_SK":3,"START_DATE":"Aug 8, 2012","COMPLETE_DATE":"Aug 8, 2012","ROWS_READ":21395,"ROWS_WRITTEN":17062,"CONTEXT_VERS":"09"},{"MODULE_RUN_SK":1982,"MODULE_SK":89,"MODULE_RUN_STATUS_SK":3,"START_DATE":"Aug 9, 2012","COMPLETE_DATE":"Aug 9, 2012","ROWS_READ":20993,"ROWS_WRITTEN":16884,"CONTEXT_VERS":"09"},{"MODULE_RUN_SK":2001,"MODULE_SK":89,"MODULE_RUN_STATUS_SK":3,"START_DATE":"Aug 10, 2012","COMPLETE_DATE":"Aug 10, 2012","ROWS_READ":17238,"ROWS_WRITTEN":13492,"CONTEXT_VERS":"09"},{"MODULE_RUN_SK":2020,"MODULE_SK":89,"MODULE_RUN_STATUS_SK":3,"START_DATE":"Aug 11, 2012","COMPLETE_DATE":"Aug 11, 2012","ROWS_READ":12702,"ROWS_WRITTEN":10509,"CONTEXT_VERS":"09"},{"MODULE_RUN_SK":1924,"MODULE_SK":89,"MODULE_RUN_STATUS_SK":2,"START_DATE":"Aug 6, 2012","COMPLETE_DATE":"Aug 6, 2012","ROWS_READ":0,"ROWS_WRITTEN":0,"CONTEXT_VERS":"09"},{"MODULE_RUN_SK":1944,"MODULE_SK":89,"MODULE_RUN_STATUS_SK":3,"START_DATE":"Aug 7, 2012","COMPLETE_DATE":"Aug 7, 2012","ROWS_READ":15624,"ROWS_WRITTEN":12675,"CONTEXT_VERS":"09"},{"MODULE_RUN_SK":2283,"MODULE_SK":89,"MODULE_RUN_STATUS_SK":3,"START_DATE":"Aug 31, 2012","COMPLETE_DATE":"Aug 31, 2012","ROWS_READ":14834,"ROWS_WRITTEN":12361,"CONTEXT_VERS":"09"},{"MODULE_RUN_SK":2416,"MODULE_SK":89,"MODULE_RUN_STATUS_SK":3,"START_DATE":"Sep 11, 2012","COMPLETE_DATE":"Sep 11, 2012","ROWS_READ":12054,"ROWS_WRITTEN":9854,"CONTEXT_VERS":"09"},{"MODULE_RUN_SK":2645,"MODULE_SK":89,"MODULE_RUN_STATUS_SK":3,"START_DATE":"Sep 27, 2012","COMPLETE_DATE":"Sep 27, 2012","ROWS_READ":18601,"ROWS_WRITTEN":15589,"CONTEXT_VERS":"09"},{"MODULE_RUN_SK":2378,"MODULE_SK":89,"MODULE_RUN_STATUS_SK":3,"START_DATE":"Sep 7, 2012","COMPLETE_DATE":"Sep 7, 2012","ROWS_READ":16818,"ROWS_WRITTEN":13771,"CONTEXT_VERS":"09"},{"MODULE_RUN_SK":2723,"MODULE_SK":89,"MODULE_RUN_STATUS_SK":3,"START_DATE":"Oct 3, 2012","COMPLETE_DATE":"Oct 3, 2012","ROWS_READ":3426,"ROWS_WRITTEN":0,"CONTEXT_VERS":"09"},{"MODULE_RUN_SK":2492,"MODULE_SK":89,"MODULE_RUN_STATUS_SK":3,"START_DATE":"Sep 15, 2012","COMPLETE_DATE":"Sep 15, 2012","ROWS_READ":10598,"ROWS_WRITTEN":9106,"CONTEXT_VERS":"09"},{"MODULE_RUN_SK":2742,"MODULE_SK":89,"MODULE_RUN_STATUS_SK":2,"START_DATE":"Oct 4, 2012","COMPLETE_DATE":"Oct 4, 2012","ROWS_READ":0,"ROWS_WRITTEN":0,"CONTEXT_VERS":"09"},{"MODULE_RUN_SK":2816,"MODULE_SK":89,"MODULE_RUN_STATUS_SK":2,"START_DATE":"Oct 9, 2012","COMPLETE_DATE":"Oct 9, 2012","ROWS_READ":0,"ROWS_WRITTEN":0,"CONTEXT_VERS":"09"},{"MODULE_RUN_SK":2988,"MODULE_SK":89,"MODULE_RUN_STATUS_SK":3,"START_DATE":"Oct 12, 2012","COMPLETE_DATE":"Oct 12, 2012","ROWS_READ":16594,"ROWS_WRITTEN":12803,"CONTEXT_VERS":"09"},{"MODULE_RUN_SK":2762,"MODULE_SK":89,"MODULE_RUN_STATUS_SK":2,"START_DATE":"Oct 5, 2012","COMPLETE_DATE":"Oct 5, 2012","ROWS_READ":0,"ROWS_WRITTEN":0,"CONTEXT_VERS":"09"},{"MODULE_RUN_SK":2893,"MODULE_SK":89,"MODULE_RUN_STATUS_SK":3,"START_DATE":"Oct 10, 2012","COMPLETE_DATE":"Oct 10, 2012","ROWS_READ":19774,"ROWS_WRITTEN":16625,"CONTEXT_VERS":"09"},{"MODULE_RUN_SK":2912,"MODULE_SK":89,"MODULE_RUN_STATUS_SK":3,"START_DATE":"Oct 10, 2012","COMPLETE_DATE":"Oct 10, 2012","ROWS_READ":14185,"ROWS_WRITTEN":11675,"CONTEXT_VERS":"09"},{"MODULE_RUN_SK":2588,"MODULE_SK":89,"MODULE_RUN_STATUS_SK":3,"START_DATE":"Sep 22, 2012","COMPLETE_DATE":"Sep 22, 2012","ROWS_READ":15320,"ROWS_WRITTEN":11586,"CONTEXT_VERS":"09"},{"MODULE_RUN_SK":2664,"MODULE_SK":89,"MODULE_RUN_STATUS_SK":3,"START_DATE":"Sep 28, 2012","COMPLETE_DATE":"Sep 28, 2012","ROWS_READ":18661,"ROWS_WRITTEN":14586,"CONTEXT_VERS":"09"},{"MODULE_RUN_SK":3064,"MODULE_SK":89,"MODULE_RUN_STATUS_SK":3,"START_DATE":"Oct 18, 2012","COMPLETE_DATE":"Oct 18, 2012","ROWS_READ":15190,"ROWS_WRITTEN":12072,"CONTEXT_VERS":"09"},{"MODULE_RUN_SK":2550,"MODULE_SK":89,"MODULE_RUN_STATUS_SK":3,"START_DATE":"Sep 20, 2012","COMPLETE_DATE":"Sep 20, 2012","ROWS_READ":23976,"ROWS_WRITTEN":18503,"CONTEXT_VERS":"09"},{"MODULE_RUN_SK":2683,"MODULE_SK":89,"MODULE_RUN_STATUS_SK":3,"START_DATE":"Sep 29, 2012","COMPLETE_DATE":"Sep 29, 2012","ROWS_READ":10662,"ROWS_WRITTEN":8699,"CONTEXT_VERS":"09"},{"MODULE_RUN_SK":3007,"MODULE_SK":89,"MODULE_RUN_STATUS_SK":3,"START_DATE":"Oct 13, 2012","COMPLETE_DATE":"Oct 13, 2012","ROWS_READ":16953,"ROWS_WRITTEN":13404,"CONTEXT_VERS":"09"},{"MODULE_RUN_SK":3045,"MODULE_SK":89,"MODULE_RUN_STATUS_SK":3,"START_DATE":"Oct 17, 2012","COMPLETE_DATE":"Oct 17, 2012","ROWS_READ":21393,"ROWS_WRITTEN":16513,"CONTEXT_VERS":"09"},{"MODULE_RUN_SK":1510,"MODULE_SK":89,"MODULE_RUN_STATUS_SK":3,"START_DATE":"Jul 6, 2012","COMPLETE_DATE":"Jul 6, 2012","ROWS_READ":20808,"ROWS_WRITTEN":15853,"CONTEXT_VERS":"09"},{"MODULE_RUN_SK":1567,"MODULE_SK":89,"MODULE_RUN_STATUS_SK":3,"START_DATE":"Jul 11, 2012","COMPLETE_DATE":"Jul 11, 2012","ROWS_READ":21299,"ROWS_WRITTEN":16623,"CONTEXT_VERS":"09"},{"MODULE_RUN_SK":1624,"MODULE_SK":89,"MODULE_RUN_STATUS_SK":3,"START_DATE":"Jul 14, 2012","COMPLETE_DATE":"Jul 14, 2012","ROWS_READ":35724,"ROWS_WRITTEN":23165,"CONTEXT_VERS":"09"},{"MODULE_RUN_SK":1776,"MODULE_SK":89,"MODULE_RUN_STATUS_SK":3,"START_DATE":"Jul 26, 2012","COMPLETE_DATE":"Jul 26, 2012","ROWS_READ":18770,"ROWS_WRITTEN":14065,"CONTEXT_VERS":"09"},{"MODULE_RUN_SK":2077,"MODULE_SK":89,"MODULE_RUN_STATUS_SK":3,"START_DATE":"Aug 16, 2012","COMPLETE_DATE":"Aug 16, 2012","ROWS_READ":18668,"ROWS_WRITTEN":14169,"CONTEXT_VERS":"09"},{"MODULE_RUN_SK":2264,"MODULE_SK":89,"MODULE_RUN_STATUS_SK":3,"START_DATE":"Aug 30, 2012","COMPLETE_DATE":"Aug 30, 2012","ROWS_READ":19632,"ROWS_WRITTEN":15571,"CONTEXT_VERS":"09"},{"MODULE_RUN_SK":2743,"MODULE_SK":89,"MODULE_RUN_STATUS_SK":3,"START_DATE":"Oct 4, 2012","COMPLETE_DATE":"Oct 4, 2012","ROWS_READ":3477,"ROWS_WRITTEN":0,"CONTEXT_VERS":"09"},{"MODULE_RUN_SK":1491,"MODULE_SK":89,"MODULE_RUN_STATUS_SK":3,"START_DATE":"Jul 5, 2012","COMPLETE_DATE":"Jul 5, 2012","ROWS_READ":20486,"ROWS_WRITTEN":16287,"CONTEXT_VERS":"09"},{"MODULE_RUN_SK":1586,"MODULE_SK":89,"MODULE_RUN_STATUS_SK":3,"START_DATE":"Jul 12, 2012","COMPLETE_DATE":"Jul 12, 2012","ROWS_READ":23031,"ROWS_WRITTEN":17979,"CONTEXT_VERS":"09"},{"MODULE_RUN_SK":1738,"MODULE_SK":89,"MODULE_RUN_STATUS_SK":3,"START_DATE":"Jul 24, 2012","COMPLETE_DATE":"Jul 24, 2012","ROWS_READ":15684,"ROWS_WRITTEN":12633,"CONTEXT_VERS":"09"},{"MODULE_RUN_SK":2359,"MODULE_SK":89,"MODULE_RUN_STATUS_SK":3,"START_DATE":"Sep 6, 2012","COMPLETE_DATE":"Sep 6, 2012","ROWS_READ":15586,"ROWS_WRITTEN":13200,"CONTEXT_VERS":"09"},{"MODULE_RUN_SK":2854,"MODULE_SK":89,"MODULE_RUN_STATUS_SK":3,"START_DATE":"Oct 9, 2012","COMPLETE_DATE":"Oct 9, 2012","ROWS_READ":18628,"ROWS_WRITTEN":15202,"CONTEXT_VERS":"09"},{"MODULE_RUN_SK":1719,"MODULE_SK":89,"MODULE_RUN_STATUS_SK":3,"START_DATE":"Jul 21, 2012","COMPLETE_DATE":"Jul 21, 2012","ROWS_READ":14447,"ROWS_WRITTEN":10900,"CONTEXT_VERS":"09"},{"MODULE_RUN_SK":2135,"MODULE_SK":89,"MODULE_RUN_STATUS_SK":3,"START_DATE":"Aug 21, 2012","COMPLETE_DATE":"Aug 21, 2012","ROWS_READ":13327,"ROWS_WRITTEN":11083,"CONTEXT_VERS":"09"},{"MODULE_RUN_SK":2531,"MODULE_SK":89,"MODULE_RUN_STATUS_SK":3,"START_DATE":"Sep 19, 2012","COMPLETE_DATE":"Sep 19, 2012","ROWS_READ":17375,"ROWS_WRITTEN":14644,"CONTEXT_VERS":"09"},{"MODULE_RUN_SK":2931,"MODULE_SK":89,"MODULE_RUN_STATUS_SK":3,"START_DATE":"Oct 10, 2012","COMPLETE_DATE":"Oct 10, 2012","ROWS_READ":12641,"ROWS_WRITTEN":10398,"CONTEXT_VERS":"09"},{"MODULE_RUN_SK":1757,"MODULE_SK":89,"MODULE_RUN_STATUS_SK":3,"START_DATE":"Jul 25, 2012","COMPLETE_DATE":"Jul 25, 2012","ROWS_READ":17458,"ROWS_WRITTEN":13978,"CONTEXT_VERS":"09"},{"MODULE_RUN_SK":2173,"MODULE_SK":89,"MODULE_RUN_STATUS_SK":3,"START_DATE":"Aug 23, 2012","COMPLETE_DATE":"Aug 23, 2012","ROWS_READ":16900,"ROWS_WRITTEN":13571,"CONTEXT_VERS":"09"},{"MODULE_RUN_SK":2302,"MODULE_SK":89,"MODULE_RUN_STATUS_SK":3,"START_DATE":"Sep 1, 2012","COMPLETE_DATE":"Sep 1, 2012","ROWS_READ":12191,"ROWS_WRITTEN":10498,"CONTEXT_VERS":"09"},{"MODULE_RUN_SK":1643,"MODULE_SK":89,"MODULE_RUN_STATUS_SK":3,"START_DATE":"Jul 17, 2012","COMPLETE_DATE":"Jul 17, 2012","ROWS_READ":14879,"ROWS_WRITTEN":11516,"CONTEXT_VERS":"09"},{"MODULE_RUN_SK":1529,"MODULE_SK":89,"MODULE_RUN_STATUS_SK":3,"START_DATE":"Jul 7, 2012","COMPLETE_DATE":"Jul 7, 2012","ROWS_READ":13609,"ROWS_WRITTEN":10282,"CONTEXT_VERS":"09"},{"MODULE_RUN_SK":1923,"MODULE_SK":89,"MODULE_RUN_STATUS_SK":2,"START_DATE":"Aug 4, 2012","COMPLETE_DATE":"Aug 4, 2012","ROWS_READ":0,"ROWS_WRITTEN":0,"CONTEXT_VERS":"09"},{"MODULE_RUN_SK":2950,"MODULE_SK":89,"MODULE_RUN_STATUS_SK":3,"START_DATE":"Oct 10, 2012","COMPLETE_DATE":"Oct 10, 2012","ROWS_READ":18619,"ROWS_WRITTEN":15068,"CONTEXT_VERS":"09"},{"MODULE_RUN_SK":2397,"MODULE_SK":89,"MODULE_RUN_STATUS_SK":3,"START_DATE":"Sep 8, 2012","COMPLETE_DATE":"Sep 8, 2012","ROWS_READ":9930,"ROWS_WRITTEN":8222,"CONTEXT_VERS":"09"},{"MODULE_RUN_SK":2454,"MODULE_SK":89,"MODULE_RUN_STATUS_SK":3,"START_DATE":"Sep 13, 2012","COMPLETE_DATE":"Sep 13, 2012","ROWS_READ":15031,"ROWS_WRITTEN":12664,"CONTEXT_VERS":"09"},{"MODULE_RUN_SK":2626,"MODULE_SK":89,"MODULE_RUN_STATUS_SK":3,"START_DATE":"Sep 26, 2012","COMPLETE_DATE":"Sep 26, 2012","ROWS_READ":19116,"ROWS_WRITTEN":15636,"CONTEXT_VERS":"09"},{"MODULE_RUN_SK":2873,"MODULE_SK":89,"MODULE_RUN_STATUS_SK":3,"START_DATE":"Oct 9, 2012","COMPLETE_DATE":"Oct 9, 2012","ROWS_READ":20214,"ROWS_WRITTEN":16737,"CONTEXT_VERS":"09"},{"MODULE_RUN_SK":3083,"MODULE_SK":89,"MODULE_RUN_STATUS_SK":3,"START_DATE":"Oct 19, 2012","COMPLETE_DATE":"Oct 19, 2012","ROWS_READ":17794,"ROWS_WRITTEN":13977,"CONTEXT_VERS":"09"},{"MODULE_RUN_SK":2512,"MODULE_SK":89,"MODULE_RUN_STATUS_SK":3,"START_DATE":"Sep 18, 2012","COMPLETE_DATE":"Sep 18, 2012","ROWS_READ":12667,"ROWS_WRITTEN":10688,"CONTEXT_VERS":"09"},{"MODULE_RUN_SK":2569,"MODULE_SK":89,"MODULE_RUN_STATUS_SK":3,"START_DATE":"Sep 21, 2012","COMPLETE_DATE":"Sep 21, 2012","ROWS_READ":15700,"ROWS_WRITTEN":13062,"CONTEXT_VERS":"09"},{"MODULE_RUN_SK":2721,"MODULE_SK":89,"MODULE_RUN_STATUS_SK":2,"START_DATE":"Oct 3, 2012","COMPLETE_DATE":"Oct 3, 2012","ROWS_READ":0,"ROWS_WRITTEN":0,"CONTEXT_VERS":"09"},{"MODULE_RUN_SK":2835,"MODULE_SK":89,"MODULE_RUN_STATUS_SK":3,"START_DATE":"Oct 9, 2012","COMPLETE_DATE":"Oct 9, 2012","ROWS_READ":13303,"ROWS_WRITTEN":11048,"CONTEXT_VERS":"09"},{"MODULE_RUN_SK":2607,"MODULE_SK":89,"MODULE_RUN_STATUS_SK":3,"START_DATE":"Sep 25, 2012","COMPLETE_DATE":"Sep 25, 2012","ROWS_READ":12173,"ROWS_WRITTEN":9879,"CONTEXT_VERS":"09"},{"MODULE_RUN_SK":2702,"MODULE_SK":89,"MODULE_RUN_STATUS_SK":3,"START_DATE":"Oct 2, 2012","COMPLETE_DATE":"Oct 2, 2012","ROWS_READ":0,"ROWS_WRITTEN":0,"CONTEXT_VERS":"09"},{"MODULE_RUN_SK":2781,"MODULE_SK":89,"MODULE_RUN_STATUS_SK":2,"START_DATE":"Oct 6, 2012","COMPLETE_DATE":"Oct 6, 2012","ROWS_READ":0,"ROWS_WRITTEN":0,"CONTEXT_VERS":"09"},{"MODULE_RUN_SK":2969,"MODULE_SK":89,"MODULE_RUN_STATUS_SK":3,"START_DATE":"Oct 11, 2012","COMPLETE_DATE":"Oct 11, 2012","ROWS_READ":17595,"ROWS_WRITTEN":14375,"CONTEXT_VERS":"09"},{"MODULE_RUN_SK":3026,"MODULE_SK":89,"MODULE_RUN_STATUS_SK":3,"START_DATE":"Oct 16, 2012","COMPLETE_DATE":"Oct 16, 2012","ROWS_READ":14069,"ROWS_WRITTEN":11565,"CONTEXT_VERS":"09"}]}